MANIFEST.in
README.rst
setup.py
collective/__init__.py
collective/__init__.pyc
collective.ptg.galleria.egg-info/PKG-INFO
collective.ptg.galleria.egg-info/SOURCES.txt
collective.ptg.galleria.egg-info/dependency_links.txt
collective.ptg.galleria.egg-info/entry_points.txt
collective.ptg.galleria.egg-info/namespace_packages.txt
collective.ptg.galleria.egg-info/not-zip-safe
collective.ptg.galleria.egg-info/requires.txt
collective.ptg.galleria.egg-info/top_level.txt
collective/ptg/__init__.py
collective/ptg/__init__.pyc
collective/ptg/galleria/__init__.py
collective/ptg/galleria/__init__.pyc
collective/ptg/galleria/configure.zcml
collective/ptg/galleria/galleria.pt
collective/ptg/galleria/i18n.sh
collective/ptg/galleria/locales/collective.ptg.galleria.pot
collective/ptg/galleria/locales/manual.pot
collective/ptg/galleria/locales/de/LC_MESSAGES/collective.ptg.galleria.mo
collective/ptg/galleria/locales/de/LC_MESSAGES/collective.ptg.galleria.po
collective/ptg/galleria/locales/es/LC_MESSAGES/collective.ptg.galleria.mo
collective/ptg/galleria/locales/es/LC_MESSAGES/collective.ptg.galleria.po
collective/ptg/galleria/locales/eu/LC_MESSAGES/collective.ptg.galleria.mo
collective/ptg/galleria/locales/eu/LC_MESSAGES/collective.ptg.galleria.po
collective/ptg/galleria/locales/fi/LC_MESSAGES/collective.ptg.galleria.mo
collective/ptg/galleria/locales/fi/LC_MESSAGES/collective.ptg.galleria.po
collective/ptg/galleria/locales/fr/LC_MESSAGES/collective.ptg.galleria.mo
collective/ptg/galleria/locales/fr/LC_MESSAGES/collective.ptg.galleria.po
collective/ptg/galleria/locales/it/LC_MESSAGES/collective.ptg.galleria.mo
collective/ptg/galleria/locales/it/LC_MESSAGES/collective.ptg.galleria.po
collective/ptg/galleria/locales/nl/LC_MESSAGES/collective.ptg.galleria.mo
collective/ptg/galleria/locales/nl/LC_MESSAGES/collective.ptg.galleria.po
collective/ptg/galleria/locales/no/LC_MESSAGES/collective.ptg.galleria.mo
collective/ptg/galleria/locales/no/LC_MESSAGES/collective.ptg.galleria.po
collective/ptg/galleria/locales/pt_BR/LC_MESSAGES/collective.ptg.galleria.mo
collective/ptg/galleria/locales/pt_BR/LC_MESSAGES/collective.ptg.galleria.po
collective/ptg/galleria/resources/classic.css
collective/ptg/galleria/resources/classic.js
collective/ptg/galleria/resources/dark.css
collective/ptg/galleria/resources/dark.js
collective/ptg/galleria/resources/fullscreen.css
