Metadata-Version: 1.0
Name: collective.ptg.galleria
Version: 1.3.0
Summary: galleria integration with plonetruegallery
Home-page: https://github.com/collective/collective.ptg.galleria
Author: Nathan Van Gheem
Author-email: vangheem@gmail.com
License: GPL
Keywords: plone plonetruegallery addon
Platform: UNKNOWN
Classifier: Framework :: Plone
Classifier: Programming Language :: Python
